__init__.py
btx_io.py
choose_best.py
compare.py
dedupe.py
second_pass.py
version.py
CITeX-0.2.2.dist-info/DESCRIPTION.rst
CITeX-0.2.2.dist-info/METADATA
CITeX-0.2.2.dist-info/RECORD
CITeX-0.2.2.dist-info/WHEEL
CITeX-0.2.2.dist-info/entry_points.txt
CITeX-0.2.2.dist-info/metadata.json
CITeX-0.2.2.dist-info/top_level.txt
